setup.cfg
setup.py
panavatar/__init__.py
panavatar/_natives.c
panavatar/_natives.pyx
panavatar/color_scheme.py
panavatar/djangoview.py
panavatar/geometry.py
panavatar/parameters.py
panavatar/patterns.py
panavatar/urls.py
panavatar.egg-info/PKG-INFO
panavatar.egg-info/SOURCES.txt
panavatar.egg-info/dependency_links.txt
panavatar.egg-info/entry_points.txt
panavatar.egg-info/top_level.txt