Metadata-Version: 1.1
Name: panavatar
Version: 0.3.3
Summary: Panavatar generates pseudorandom abstract wallpapers
Home-page: https://github.com/ondergetekende/python-panavatar
Author: Koert van der Veer
Author-email: koert@ondergetekende.nl
License: UNKNOWN
Platform: UNKNOWN
Classifier: Intended Audience :: Developers
Classifier: Operating System :: OS Independent
Classifier: Programming Language :: Python
Classifier: Programming Language :: Python :: 3
